quantiphy/__init__.py
quantiphy/__init__.pyi
quantiphy/py.typed
quantiphy/quantiphy.py
quantiphy/quantiphy.pyi
quantiphy-2.21.dist-info/licenses/LICENSE
quantiphy-2.21.dist-info/WHEEL
quantiphy-2.21.dist-info/METADATA
quantiphy-2.21.dist-info/RECORD
