Metadata-Version: 2.4
Name: quantiphy
Version: 2.21
Summary: physical quantities (numbers with units)
Keywords: quantities,physical quantity,units,SI scale factors,engineering notation,mks,cgs
Author: Ken Kundert
Author-email: quantiphy@nurdletech.com
Requires-Python: >=3.6
Classifier: Development Status :: 5 - Production/Stable
Classifier: Intended Audience :: Developers
Classifier: Intended Audience :: Science/Research
Classifier: License :: OSI Approved :: MIT License
Classifier: Natural Language :: English
Classifier: Operating System :: POSIX :: Linux
Classifier: Programming Language :: Python :: 3
Classifier: Topic :: Utilities
Classifier: Topic :: Scientific/Engineering
License-File: LICENSE
Project-URL: changelog, https://github.com/KenKundert/quantiphy/blob/master/doc/releases.rst
Project-URL: documentation, https://quantiphy.readthedocs.io
Project-URL: homepage, https://quantiphy.readthedocs.io
Project-URL: repository, https://github.com/kenkundert/quantiphy
